CHANGES.txt
MANIFEST.in
README.md
requirements.txt
setup.py
docker_tutorial/__init__.py
docker_tutorial/admin.py
docker_tutorial/models.py
docker_tutorial/urls.py
docker_tutorial/utils.py
docker_tutorial/views.py
docker_tutorial.egg-info/PKG-INFO
docker_tutorial.egg-info/SOURCES.txt
docker_tutorial.egg-info/dependency_links.txt
docker_tutorial.egg-info/top_level.txt
docker_tutorial/migrations/0001_initial.py
docker_tutorial/migrations/0002_auto__add_subscriber__add_unique_subscriber_email_from_level__add_dock.py
docker_tutorial/migrations/0003_auto__add_field_tutorialuser_http_user_agent__add_field_tutorialuser_h.py
docker_tutorial/migrations/0004_auto__del_field_tutorialuser_http_accept_encoding__add_field_tutorialu.py
docker_tutorial/migrations/0005_auto__chg_field_tutorialuser_http_user_agent__chg_field_tutorialuser_h.py
docker_tutorial/migrations/__init__.py
docker_tutorial/static/css/tutorial-style.css
docker_tutorial/static/css/tutorial-style.less
docker_tutorial/static/img/circle-green.svg
docker_tutorial/static/img/docker-letters.png
docker_tutorial/static/img/docker-topicon.png
docker_tutorial/static/img/email.png
docker_tutorial/static/img/facebook.png
docker_tutorial/static/img/favicon.png
docker_tutorial/static/img/fullscreen_exit_32x32.png
docker_tutorial/static/img/twitter.png
docker_tutorial/static/js/steps.coffee
docker_tutorial/static/js/steps.js
docker_tutorial/static/js/terminal.coffee
docker_tutorial/static/js/terminal.js
docker_tutorial/static/lib/css/jquery.terminal.css
docker_tutorial/static/lib/js/jquery-1.7.1.min.js
docker_tutorial/static/lib/js/jquery.mousewheel-min.js
docker_tutorial/static/lib/js/jquery.terminal-0.7.4.js
docker_tutorial/static/lib/js/jquery.terminal-0.7.4.min.js
docker_tutorial/static/lib/js/sugar-1.3.9.min.js
docker_tutorial/templates/tutorial/snippet.html
docker_tutorial/templates/tutorial/stats.html
docker_tutorial/templates/tutorial/testpage.html
docker_tutorial/tests/__init__.py
docker_tutorial/tests/test_views.py
dockerfile_tutorial/__init__.py
dockerfile_tutorial/urls.py
dockerfile_tutorial/static/css/dockerfile_tutorial.css
