Metadata-Version: 1.0
Name: docker-tutorial
Version: 0.2.1
Summary: An interactive learning environment to get familiar with the Docker cli
Home-page: https://github.com/dhrp/docker-tutorial/
Author: Thatcher Peskens
Author-email: thatcher@dotcloud.com
License: To be determined
Platform: UNKNOWN
